MANIFEST.in
README.md
pyproject.toml
setup.py
pagecache/__init__.py
pagecache/cli.py
pagecache/configure_logging.py
pagecache/exceptions.py
pagecache/pagecache_monitor.py
pagecache/src/cachemodule.c
pagecache_ttl.egg-info/PKG-INFO
pagecache_ttl.egg-info/SOURCES.txt
pagecache_ttl.egg-info/dependency_links.txt
pagecache_ttl.egg-info/entry_points.txt
pagecache_ttl.egg-info/not-zip-safe
pagecache_ttl.egg-info/requires.txt
pagecache_ttl.egg-info/top_level.txt
requirements/requirements.txt